odoo/addons/product_attribute_value_archive/README.rst
odoo/addons/product_attribute_value_archive/__init__.py
odoo/addons/product_attribute_value_archive/__manifest__.py
odoo/addons/product_attribute_value_archive/i18n/it.po
odoo/addons/product_attribute_value_archive/i18n/product_attribute_value_archive.pot
odoo/addons/product_attribute_value_archive/models/__init__.py
odoo/addons/product_attribute_value_archive/models/product_attribute_value.py
odoo/addons/product_attribute_value_archive/models/product_product.py
odoo/addons/product_attribute_value_archive/models/product_template_attribute_value.py
odoo/addons/product_attribute_value_archive/readme/CONTRIBUTORS.rst
odoo/addons/product_attribute_value_archive/readme/DESCRIPTION.rst
odoo/addons/product_attribute_value_archive/static/description/icon.png
odoo/addons/product_attribute_value_archive/static/description/index.html
odoo/addons/product_attribute_value_archive/tests/__init__.py
odoo/addons/product_attribute_value_archive/tests/test_archive_attribute_value.py
odoo13_addon_product_attribute_value_archive-13.0.1.0.1.dev6.dist-info/METADATA
odoo13_addon_product_attribute_value_archive-13.0.1.0.1.dev6.dist-info/WHEEL
odoo13_addon_product_attribute_value_archive-13.0.1.0.1.dev6.dist-info/top_level.txt
odoo13_addon_product_attribute_value_archive-13.0.1.0.1.dev6.dist-info/RECORD
